MANIFEST.in
README.md
setup.py
OASYS1_WOFRY.egg-info/PKG-INFO
OASYS1_WOFRY.egg-info/SOURCES.txt
OASYS1_WOFRY.egg-info/dependency_links.txt
OASYS1_WOFRY.egg-info/entry_points.txt
OASYS1_WOFRY.egg-info/namespace_packages.txt
OASYS1_WOFRY.egg-info/not-zip-safe
OASYS1_WOFRY.egg-info/requires.txt
OASYS1_WOFRY.egg-info/top_level.txt
orangecontrib/__init__.py
orangecontrib/wofry/__init__.py
orangecontrib/wofry/util/wofry_objects.py
orangecontrib/wofry/util/wofry_util.py
orangecontrib/wofry/widgets/__init__.py
orangecontrib/wofry/widgets/beamline_elements/__init__.py
orangecontrib/wofry/widgets/beamline_elements/ow_double_slit.py
orangecontrib/wofry/widgets/beamline_elements/ow_gaussian_slits_1d.py
orangecontrib/wofry/widgets/beamline_elements/ow_ideal_lens.py
orangecontrib/wofry/widgets/beamline_elements/ow_ideal_lens_1d.py
orangecontrib/wofry/widgets/beamline_elements/ow_mirror_1d.py
orangecontrib/wofry/widgets/beamline_elements/ow_real_lens_1d.py
orangecontrib/wofry/widgets/beamline_elements/ow_real_lens_2d.py
orangecontrib/wofry/widgets/beamline_elements/ow_screen.py
orangecontrib/wofry/widgets/beamline_elements/ow_screen_1d.py
orangecontrib/wofry/widgets/beamline_elements/ow_slits.py
orangecontrib/wofry/widgets/beamline_elements/ow_slits_1d.py
orangecontrib/wofry/widgets/beamline_elements/ow_stop.py
orangecontrib/wofry/widgets/beamline_elements/ow_stop_1d.py
orangecontrib/wofry/widgets/beamline_elements/ow_thin_object_1d.py
orangecontrib/wofry/widgets/beamline_elements/ow_thin_object_2d.py
orangecontrib/wofry/widgets/beamline_elements/ow_thin_object_corrector_1d.py
orangecontrib/wofry/widgets/beamline_elements/ow_thin_object_corrector_2d.py
orangecontrib/wofry/widgets/beamline_elements/icons/beamline_elements.png
orangecontrib/wofry/widgets/beamline_elements/icons/corrector1d.png
orangecontrib/wofry/widgets/beamline_elements/icons/corrector2d.png
orangecontrib/wofry/widgets/beamline_elements/icons/double_slit.png
orangecontrib/wofry/widgets/beamline_elements/icons/ideal_lens1d.png
orangecontrib/wofry/widgets/beamline_elements/icons/ideal_lens2d.png
orangecontrib/wofry/widgets/beamline_elements/icons/lens1d.png
orangecontrib/wofry/widgets/beamline_elements/icons/lens2d.png
orangecontrib/wofry/widgets/beamline_elements/icons/obsolete.png
